flask_uuid_utils.py
flask_uuid_utils-0.1.0.dist-info/RECORD
flask_uuid_utils-0.1.0.dist-info/DESCRIPTION.rst
flask_uuid_utils-0.1.0.dist-info/top_level.txt
flask_uuid_utils-0.1.0.dist-info/METADATA
flask_uuid_utils-0.1.0.dist-info/WHEEL
flask_uuid_utils-0.1.0.dist-info/metadata.json
